backuptools/__init__.py
backuptools/__main__.py
backuptools/backuptools.py
backuptools/googledriveclient.py
backuptools/type.py
backuptools-1.0.1.dist-info/LICENSE
backuptools-1.0.1.dist-info/METADATA
backuptools-1.0.1.dist-info/WHEEL
backuptools-1.0.1.dist-info/entry_points.txt
backuptools-1.0.1.dist-info/top_level.txt
backuptools-1.0.1.dist-info/RECORD
