Metadata-Version: 2.1
Name: backuptools
Version: 1.0.1
Summary: Backup, restore, version control local data to google drive
Home-page: https://github.com/hieunv495/backuptools
Author: hieunv495
Author-email: hieunv495@gmail.com
License: UNKNOWN
Project-URL: Bug Tracker, https://github.com/hieunv495/backuptools/issues
Platform: UNKNOWN
Classifier: Programming Language :: Python :: 3
Classifier: License :: OSI Approved :: MIT License
Classifier: Operating System :: OS Independent
Requires-Python: >=3.6
License-File: LICENSE
Requires-Dist: google-api-python-client (>=2.15.0)
Requires-Dist: google-auth-httplib2 (>=0.1.0)
Requires-Dist: python-magic (>=0.4.10)
Requires-Dist: checksumdir (>=1.2.0)
Requires-Dist: click
